autoetl/__init__.py
autoetl/__main__.py
autoetl/cli.py
autoetl/config.py
autoetl-0.1.0.dist-info/LICENSE
autoetl-0.1.0.dist-info/METADATA
autoetl-0.1.0.dist-info/WHEEL
autoetl-0.1.0.dist-info/entry_points.txt
autoetl-0.1.0.dist-info/RECORD
