Metadata-Version: 2.1
Name: autoetl
Version: 0.1.0
Summary: Wire up APIs with databases in minutes. Ingest, persist, enrich, merge and serve data automagically.
License: AGPL-3.0
Author: Sean Kruzel
Author-email: sean@closedloop.tech
Requires-Python: >=3.10,<4.0
Classifier: License :: OSI Approved :: GNU Affero General Public License v3
Classifier: Operating System :: OS Independent
Classifier: Programming Language :: Python :: 3
Classifier: Programming Language :: Python :: 3.10
Classifier: Programming Language :: Python :: 3.11
Classifier: Programming Language :: Python :: 3.12
Classifier: Topic :: Software Development :: Libraries :: Python Modules
Requires-Dist: colorama (>=0.4.6,<0.5.0)
Requires-Dist: gcloud (>=0.18.3,<0.19.0)
Requires-Dist: pre-commit (>=3.6.0,<4.0.0)
Requires-Dist: pyfiglet (>=1.0.2,<2.0.0)
Requires-Dist: python-dotenv (>=1.0.0,<2.0.0)
Requires-Dist: tabulate (>=0.9.0,<0.10.0)
Requires-Dist: termcolor (>=2.4.0,<3.0.0)
Requires-Dist: twine (>=4.0.2,<5.0.0)
Requires-Dist: typer (>=0.9.0,<0.10.0)
Project-URL: Bug Tracker, https://github.com/closedLoop/autoetl/issues
Project-URL: Repository, https://github.com/closedLoop/autoetl
